{"cameraMode":{"drawMode":0,"name":"Shaded","section":"Shading Mode"},"sceneLighting":true,"audioPlay":false,"sceneViewState":{"m_AlwaysRefresh":false,"showFog":true,"showSkybox":true,"showFlares":true,"showImageEffects":true,"showParticleSystems":true,"showVisualEffectGraphs":true,"m_FxEnabled":true},"in2DMode":false,"pivot":{"x":-723.1846923828125,"y":-504.5854187011719,"z":204.27749633789063},"rotation":{"x":0.23297499120235444,"y":-0.5773096680641174,"z":0.17623649537563325,"w":0.7626925706863403},"size":457.2951965332031,"orthographic":false}